clustering_eval/__init__.py
clustering_eval/ncqi.py
clustering_eval-0.1.1.dist-info/METADATA
clustering_eval-0.1.1.dist-info/WHEEL
clustering_eval-0.1.1.dist-info/top_level.txt
clustering_eval-0.1.1.dist-info/RECORD
